[
    {
        "titulo": "Mercado Central, Megaleite e mais: a agenda de Flávio Bolsonaro em BH",
        "descricao": "Senador dividirá agendas com outros dois pré-candidatos à Presidência: Romeu Zema e Ronaldo Caiado",
        "imagem": "https://midias.em.com.br/_midias/png/2026/03/15/1200x720/1_flavio-bolsonaro-65302119.png?20260415105856?20260415105856",
        "fonte": "estadodeminas",
        "link": "https://www.em.com.br/politica/2026/05/7431244-mercado-central-megaleite-e-mais-a-agenda-de-flavio-bolsonaro-em-bh.html",
        "data": "2026-05-29 19:44:00"
    },
    {
        "titulo": "Parlamento de Gana aprova lei anti-LGBT+",
        "descricao": "Texto prevê até três anos de prisão para qualquer pessoa que tenha mantido relações homossexuais",
        "imagem": "https://odia.ig.com.br/_midias/jpg/2024/08/08/lgbt-33658425.jpeg",
        "fonte": "odia_ig_br",
        "link": "https://odia.ig.com.br/mundo-e-ciencia/2026/05/7258319-parlamento-de-gana-aprova-lei-anti-lgbt-.html",
        "data": "2026-05-29 19:43:25"
    },
    {
        "titulo": "Paula Lima lança o single “D’Ouro Brilhante” e abre caminhos para nova era musical",
        "descricao": "Paula Lima lançou hoje (28) o single “D’Ouro Brilhante”, faixa que marca o início de uma nova fase em sua trajetória artística. A canção, composta por Di Melo The post Paula Lima lança o single “D’Ouro Brilhante” e abre caminhos para nova era musical appeared first on Diário da Manhã - O Jornal do leitor Inteligente .",
        "imagem": "https://www.dm.com.br/wp-content/uploads/2026/05/WhatsApp-Image-2026-05-29-at-4.07.52-PM.jpeg",
        "fonte": "dm",
        "link": "https://www.dm.com.br/entretenimento/paula-lima-lanca-o-single-douro-brilhante-e-abre-caminhos-para-nova-era-musical/",
        "data": "2026-05-29 19:43:20"
    },
    {
        "titulo": "Escalação: Palmeiras pode ter retorno de zagueiro contra a Chapecoense",
        "descricao": "O Palmeiras iniciou sua preparação para o confronto diante da Chapecoense, no próximo domingo ...",
        "imagem": "https://p2.trrsf.com/image/fget/cf/1200/900/middle/images.terra.com/2026/05/29/1534763626-29052026cgpalmeiras15227easy-resizecom-610x400.jpg",
        "fonte": "terra",
        "link": "https://www.terra.com.br/esportes/palmeiras/escalacao-palmeiras-pode-ter-retorno-de-zagueiro-contra-a-chapecoense,c66e2ebd4d834662c9300fa47f194bf3qpbg81k8.html",
        "data": "2026-05-29 19:43:13"
    },
    {
        "titulo": "Lateral está fora dos planos do Grêmio",
        "descricao": "João Pedro pode ser negociado na próxima janela de transferências",
        "imagem": "",
        "fonte": "correiodopovo",
        "link": "https://www.correiodopovo.com.br/esportes/gr%C3%AAmio/lateral-esta-fora-dos-planos-do-gremio-1.1717917",
        "data": "2026-05-29 19:43:13"
    },
    {
        "titulo": "A Viagem: as diferenças entre a novela e o filme",
        "descricao": "Saiba as diferenças percebidas entre a novela de 1994 e o filme baseado na obra O lançamento do ...",
        "imagem": "https://p2.trrsf.com/image/fget/cf/1200/900/middle/images.terra.com/2026/05/29/589005200-foto-3-reproducao-internet.jpg",
        "fonte": "terra",
        "link": "https://www.terra.com.br/vida-e-estilo/a-viagem-as-diferencas-entre-a-novela-e-o-filme,2ef2ae1ef11fb6ad3832899c511bdf11kh9iy6i2.html",
        "data": "2026-05-29 19:43:08"
    },
    {
        "titulo": "Festival de Dança de Pinhais terá apresentações gratuitas neste fim de semana",
        "descricao": "Pinhais recebe neste sábado (30) e domingo (31) a 7a edição do Festival de Dança de Pinhais. O evento será... O post Festival de Dança de Pinhais terá apresentações gratuitas neste fim de semana apareceu primeiro em Bem Paraná .",
        "imagem": "https://www.bemparana.com.br/wp-content/uploads/2026/05/img_A49FD38CFB1598497FDC8A6ED83DD49C4BEF1826_607x1120.jpg",
        "fonte": "bemparana_br",
        "link": "https://www.bemparana.com.br/noticias/regiao-metropolitana/festival-de-danca-de-pinhais-tera-apresentacoes-gratuitas-neste-fim-de-semana/",
        "data": "2026-05-29 19:43:02"
    },
    {
        "titulo": "Câmara aprova reajuste de servidores e regras para magistério",
        "descricao": "Vereadores da Câmara Municipal de Corumbá aprovaram o reajuste de 4,39% aos servidores efetivos e contratados em geral, correspondente à variação acumulada do Índice Nacional de Preços ao Consumidor Amplo (IPCA) no período entre maio de 2025 e abril de 2026.",
        "imagem": "https://cdn.capitalnews.com.br/storage/webdisco/2026/05/27/1200x900/d2dfa7f816b55f1a98619af2a326dfee-capitalnews-com-br.jpg",
        "fonte": "capitalnews",
        "link": "https://www.capitalnews.com.br/politica-e-poder/legislativo/camara-aprova-reajuste-de-servidores-e-regras-para-magisterio/441210",
        "data": "2026-05-29 19:43:00"
    },
    {
        "titulo": "Como resolver umidade no rodapé da parede sem errar no produto e sem reformar duas vezes",
        "descricao": "Saiba como resolver umidade na parede sem jogar dinheiro fora, corrigindo a origem da água antes de refazer pintura e acabamento The post Como resolver umidade no rodapé da parede sem errar no produto e sem reformar duas vezes appeared first on O Antagonista .",
        "imagem": "https://cdn.oantagonista.com/uploads/2026/05/Mancha_umidade_pintura_descascan%E2%80%A6_202605271542.jpg",
        "fonte": "oantagonista",
        "link": "https://oantagonista.com.br/ladooa/entretenimento/como-resolver-umidade-no-rodape-da-parede-sem-errar-no-produto-e-sem-reformar-duas-vezes/",
        "data": "2026-05-29 19:43:00"
    },
    {
        "titulo": "Vistoria encontra livros que não fazem parte da grade curricular dos alunos da rede municipal",
        "descricao": "",
        "imagem": "https://odocumento.com.br/content/images/2026/05/a-a-37.jpg",
        "fonte": "odocumento",
        "link": "https://odocumento.com.br/vistoria-encontra-livros-que-nao-fazem-parte-da-grade-curricular-dos-alunos-da-rede-municipal/",
        "data": "2026-05-29 19:43:00"
    }
]